api/__init__.py
api/main.py
api/q_a.py
api/table_format.py
pdf_table_processor-1.1.2.dist-info/METADATA
pdf_table_processor-1.1.2.dist-info/WHEEL
pdf_table_processor-1.1.2.dist-info/entry_points.txt
pdf_table_processor-1.1.2.dist-info/top_level.txt
pdf_table_processor-1.1.2.dist-info/RECORD
