Metadata-Version: 2.2
Name: pdf_table_processor
Version: 1.1.2
Home-page: https://github.com/klncgty/Pdf_Table_Extractor
Author: Çağatay
Author-email: cgtyklnc@gmail.com
Requires-Dist: fastapi
Requires-Dist: uvicorn
Requires-Dist: pandas
Requires-Dist: pandasai
Requires-Dist: gmft
Requires-Dist: matplotlib
Requires-Dist: pillow
Requires-Dist: PyPDF2
Dynamic: author
Dynamic: author-email
Dynamic: description
Dynamic: home-page
Dynamic: requires-dist
